{
  "date": "2026-04-01",
  "collected_at": "2026-04-01T06:10:52.127Z",
  "videos": {
    "BV1QVXUBpE91": {
      "view": 44707,
      "like": 952,
      "favorite": 74,
      "coin": 83,
      "share": 143,
      "danmaku": 76,
      "reply": 784
    },
    "BV1paXUBgEZv": {
      "view": 19727,
      "like": 679,
      "favorite": 41,
      "coin": 59,
      "share": 35,
      "danmaku": 53,
      "reply": 207
    },
    "BV1mWXUB1E5y": {
      "view": 20452,
      "like": 593,
      "favorite": 38,
      "coin": 41,
      "share": 39,
      "danmaku": 44,
      "reply": 186
    },
    "BV114XUBCEbs": {
      "view": 17394,
      "like": 608,
      "favorite": 28,
      "coin": 56,
      "share": 23,
      "danmaku": 24,
      "reply": 186
    },
    "BV1yUXmBzEVw": {
      "view": 81213,
      "like": 1408,
      "favorite": 237,
      "coin": 130,
      "share": 326,
      "danmaku": 97,
      "reply": 399
    },
    "BV1WHQmBNE3X": {
      "view": 98000,
      "like": 2112,
      "favorite": 328,
      "coin": 302,
      "share": 581,
      "danmaku": 201,
      "reply": 1394
    },
    "BV1sQQRBoEKX": {
      "view": 104351,
      "like": 1859,
      "favorite": 163,
      "coin": 150,
      "share": 824,
      "danmaku": 254,
      "reply": 1213
    },
    "BV16yQdBHE7q": {
      "view": 58058,
      "like": 1202,
      "favorite": 91,
      "coin": 158,
      "share": 222,
      "danmaku": 111,
      "reply": 1163
    },
    "BV1MxQdBeEzV": {
      "view": 72706,
      "like": 1703,
      "favorite": 145,
      "coin": 276,
      "share": 492,
      "danmaku": 253,
      "reply": 931
    },
    "BV1yTAwzTEZp": {
      "view": 134995,
      "like": 2451,
      "favorite": 399,
      "coin": 218,
      "share": 931,
      "danmaku": 250,
      "reply": 1212
    },
    "BV1unQ9BFEux": {
      "view": 106503,
      "like": 1691,
      "favorite": 147,
      "coin": 139,
      "share": 530,
      "danmaku": 153,
      "reply": 1560
    },
    "BV1uez4BpEMD": {
      "view": 72387,
      "like": 1533,
      "favorite": 144,
      "coin": 149,
      "share": 464,
      "danmaku": 0,
      "reply": 1090
    },
    "BV1yfzWBBEAy": {
      "view": 52198,
      "like": 1151,
      "favorite": 107,
      "coin": 138,
      "share": 208,
      "danmaku": 0,
      "reply": 768
    },
    "BV1wNQqBKEhu": {
      "view": 54479,
      "like": 1034,
      "favorite": 100,
      "coin": 88,
      "share": 90,
      "danmaku": 32,
      "reply": 657
    },
    "BV1z86RBQEdD": {
      "view": 53096,
      "like": 1105,
      "favorite": 124,
      "coin": 111,
      "share": 119,
      "danmaku": 0,
      "reply": 739
    },
    "BV1memyB9ExY": {
      "view": 32886,
      "like": 797,
      "favorite": 112,
      "coin": 53,
      "share": 70,
      "danmaku": 0,
      "reply": 486
    },
    "BV1iUXzBqEdu": {
      "view": 80928,
      "like": 1467,
      "favorite": 212,
      "coin": 105,
      "share": 176,
      "danmaku": 76,
      "reply": 875
    },
    "BV1jaX6BMEP6": {
      "view": 25569,
      "like": 657,
      "favorite": 36,
      "coin": 30,
      "share": 16,
      "danmaku": 22,
      "reply": 335
    },
    "BV1X9XqBxExz": {
      "view": 33975,
      "like": 704,
      "favorite": 43,
      "coin": 45,
      "share": 64,
      "danmaku": 61,
      "reply": 290
    },
    "BV1frXqBeE7c": {
      "view": 36821,
      "like": 814,
      "favorite": 89,
      "coin": 57,
      "share": 67,
      "danmaku": 62,
      "reply": 238
    },
    "BV1EQXaBpES6": {
      "view": 42341,
      "like": 1065,
      "favorite": 97,
      "coin": 135,
      "share": 78,
      "danmaku": 51,
      "reply": 416
    },
    "BV1pkXaBbEBj": {
      "view": 35731,
      "like": 878,
      "favorite": 84,
      "coin": 80,
      "share": 118,
      "danmaku": 67,
      "reply": 338
    },
    "BV1AxXYBFEAT": {
      "view": 27633,
      "like": 799,
      "favorite": 66,
      "coin": 50,
      "share": 84,
      "danmaku": 57,
      "reply": 308
    },
    "BV1L7XaB1ETf": {
      "view": 44789,
      "like": 1015,
      "favorite": 89,
      "coin": 95,
      "share": 85,
      "danmaku": 60,
      "reply": 574
    },
    "BV1SQXdBzEXe": {
      "view": 68861,
      "like": 1234,
      "favorite": 225,
      "coin": 76,
      "share": 75,
      "danmaku": 38,
      "reply": 335
    },
    "BV1pMXoBfEWN": {
      "view": 22977,
      "like": 668,
      "favorite": 37,
      "coin": 57,
      "share": 63,
      "danmaku": 47,
      "reply": 326
    },
    "BV14zXoBqExZ": {
      "view": 21387,
      "like": 668,
      "favorite": 39,
      "coin": 68,
      "share": 75,
      "danmaku": 31,
      "reply": 319
    },
    "BV1NGXQBDE9y": {
      "view": 41708,
      "like": 1134,
      "favorite": 126,
      "coin": 199,
      "share": 138,
      "danmaku": 110,
      "reply": 710
    },
    "BV1s5XQBJEMz": {
      "view": 29801,
      "like": 888,
      "favorite": 64,
      "coin": 118,
      "share": 113,
      "danmaku": 71,
      "reply": 327
    },
    "BV18HXDBREs3": {
      "view": 46268,
      "like": 1160,
      "favorite": 121,
      "coin": 161,
      "share": 348,
      "danmaku": 127,
      "reply": 823
    },
    "BV1SBXmBjE4J": {
      "view": 20381,
      "like": 619,
      "favorite": 35,
      "coin": 45,
      "share": 15,
      "danmaku": 8,
      "reply": 170
    },
    "BV1YgX5B4EEf": {
      "view": 32931,
      "like": 831,
      "favorite": 48,
      "coin": 61,
      "share": 45,
      "danmaku": 31,
      "reply": 372
    },
    "BV1YZXTB3E9E": {
      "view": 31841,
      "like": 939,
      "favorite": 72,
      "coin": 132,
      "share": 54,
      "danmaku": 54,
      "reply": 331
    },
    "BV1hwXMBBEe9": {
      "view": 18017,
      "like": 532,
      "favorite": 29,
      "coin": 32,
      "share": 38,
      "danmaku": 7,
      "reply": 148
    },
    "BV1oYXMB7E6L": {
      "view": 28268,
      "like": 870,
      "favorite": 44,
      "coin": 159,
      "share": 45,
      "danmaku": 39,
      "reply": 289
    },
    "BV1hRXABoEvc": {
      "view": 27253,
      "like": 762,
      "favorite": 58,
      "coin": 73,
      "share": 62,
      "danmaku": 30,
      "reply": 334
    },
    "BV1gBXPBtE5V": {
      "view": 47087,
      "like": 975,
      "favorite": 83,
      "coin": 51,
      "share": 119,
      "danmaku": 28,
      "reply": 475
    },
    "BV1BpXPBBEjY": {
      "view": 23948,
      "like": 730,
      "favorite": 45,
      "coin": 69,
      "share": 50,
      "danmaku": 59,
      "reply": 242
    },
    "BV13EXNBcEW5": {
      "view": 32933,
      "like": 886,
      "favorite": 126,
      "coin": 76,
      "share": 64,
      "danmaku": 22,
      "reply": 409
    },
    "BV1JvXWBwERy": {
      "view": 70044,
      "like": 1443,
      "favorite": 104,
      "coin": 194,
      "share": 669,
      "danmaku": 170,
      "reply": 761
    },
    "BV1x1XsB5Erj": {
      "view": 39616,
      "like": 1034,
      "favorite": 51,
      "coin": 87,
      "share": 62,
      "danmaku": 125,
      "reply": 444
    },
    "BV1FgXpB8EvF": {
      "view": 46777,
      "like": 1173,
      "favorite": 72,
      "coin": 140,
      "share": 78,
      "danmaku": 101,
      "reply": 600
    }
  }
}